figaroh/__init__.py
figaroh/calibration/__init__.py
figaroh/calibration/base_calibration.py
figaroh/calibration/calibration_tools.py
figaroh/calibration/config.py
figaroh/calibration/data_loader.py
figaroh/calibration/parameter.py
figaroh/identification/__init__.py
figaroh/identification/base_identification.py
figaroh/identification/config.py
figaroh/identification/identification_tools.py
figaroh/identification/parameter.py
figaroh/measurements/__init__.py
figaroh/measurements/measurement.py
figaroh/optimal/__init__.py
figaroh/optimal/base_optimal_calibration.py
figaroh/optimal/base_optimal_trajectory.py
figaroh/tools/__init__.py
figaroh/tools/load_robot.py
figaroh/tools/qrdecomposition.py
figaroh/tools/randomdata.py
figaroh/tools/regressor.py
figaroh/tools/robot.py
figaroh/tools/robotcollisions.py
figaroh/tools/robotipopt.py
figaroh/tools/robotvisualization.py
figaroh/tools/solver.py
figaroh/utils/__init__.py
figaroh/utils/config_parser.py
figaroh/utils/cubic_spline.py
figaroh/utils/error_handling.py
figaroh/utils/results_manager.py
figaroh/visualisation/__init__.py
figaroh/visualisation/colors.py
figaroh/visualisation/visualizer.py
figaroh-0.3.0.dist-info/METADATA
figaroh-0.3.0.dist-info/WHEEL
figaroh-0.3.0.dist-info/licenses/LICENSE
figaroh-0.3.0.dist-info/RECORD
