Metadata-Version: 2.4
Name: figaroh
Version: 0.3.0
Summary: A Python toolbox for dynamics identification and geometric calibration of robots and humans
Project-URL: Homepage, https://github.com/thanhndv212/figaroh-plus
Project-URL: Repository, https://github.com/thanhndv212/figaroh-plus
Project-URL: Issues, https://github.com/thanhndv212/figaroh-plus/issues
Project-URL: Examples, https://github.com/thanhndv212/figaroh-examples
Author-email: "Thanh D. V. Nguyen" <thanhndv212@gmail.com>
Maintainer-email: "Thanh D. V. Nguyen" <thanhndv212@gmail.com>
License: Copyright 2025 Thanh D. V. Nguyen
License-File: LICENSE
Keywords: calibration,dynamics,identification,optimization,pinocchio,robotics,urdf
Classifier: Development Status :: 4 - Beta
Classifier: Intended Audience :: Developers
Classifier: Intended Audience :: Science/Research
Classifier: License :: OSI Approved :: BSD License
Classifier: Operating System :: OS Independent
Classifier: Programming Language :: Python :: 3
Classifier: Programming Language :: Python :: 3.8
Classifier: Programming Language :: Python :: 3.9
Classifier: Programming Language :: Python :: 3.10
Classifier: Programming Language :: Python :: 3.11
Classifier: Programming Language :: Python :: 3.12
Classifier: Topic :: Scientific/Engineering :: Artificial Intelligence
Classifier: Topic :: Scientific/Engineering :: Physics
Classifier: Topic :: Software Development :: Libraries :: Python Modules
Requires-Python: >=3.8
Requires-Dist: matplotlib
Requires-Dist: meshcat
Requires-Dist: ndcurves
Requires-Dist: numdifftools
Requires-Dist: numpy
Requires-Dist: pandas
Requires-Dist: picos
Requires-Dist: pin
Requires-Dist: pyyaml
Requires-Dist: rospkg
Requires-Dist: scipy
Provides-Extra: dev
Requires-Dist: black; extra == 'dev'
Requires-Dist: flake8; extra == 'dev'
Requires-Dist: isort; extra == 'dev'
Requires-Dist: mypy; extra == 'dev'
Requires-Dist: pre-commit; extra == 'dev'
Requires-Dist: pytest-cov; extra == 'dev'
Requires-Dist: pytest>=6.0; extra == 'dev'
Provides-Extra: docs
Requires-Dist: sphinx; extra == 'docs'
Requires-Dist: sphinx-autodoc-typehints; extra == 'docs'
Requires-Dist: sphinx-rtd-theme; extra == 'docs'
Provides-Extra: examples
Requires-Dist: ipywidgets; extra == 'examples'
Requires-Dist: jupyter; extra == 'examples'
Requires-Dist: notebook; extra == 'examples'
